geotwit/__init__.py
geotwit/test.py
geotwit/twitter_scraper.py
geotwit-0.0.2.dist-info/LICENSE
geotwit-0.0.2.dist-info/METADATA
geotwit-0.0.2.dist-info/WHEEL
geotwit-0.0.2.dist-info/top_level.txt
geotwit-0.0.2.dist-info/RECORD
